test_poc_confused_2/main.py
test_poc_confused_2-99.99.99.dist-info/METADATA
test_poc_confused_2-99.99.99.dist-info/WHEEL
test_poc_confused_2-99.99.99.dist-info/RECORD
